lnctApi/__init__.py
lnctApi/accsoft_api.py
lnctApi-0.0.6.dist-info/LICENSE.txt
lnctApi-0.0.6.dist-info/METADATA
lnctApi-0.0.6.dist-info/WHEEL
lnctApi-0.0.6.dist-info/top_level.txt
lnctApi-0.0.6.dist-info/RECORD
